microsoft_skala-1.1.1.dist-info/licenses/LICENSE.txt
skala/__init__.py
skala/py.typed
skala/ase/__init__.py
skala/ase/calculator.py
skala/foundry/__init__.py
skala/foundry/client.py
skala/foundry/schemas.py
skala/functional/__init__.py
skala/functional/base.py
skala/functional/density.py
skala/functional/layers.py
skala/functional/load.py
skala/functional/model.py
skala/functional/traditional.py
skala/gpu4pyscf/__init__.py
skala/gpu4pyscf/dft.py
skala/gpu4pyscf/gradients.py
skala/pyscf/__init__.py
skala/pyscf/backend.py
skala/pyscf/dft.py
skala/pyscf/features.py
skala/pyscf/gradients.py
skala/pyscf/numint.py
skala/pyscf/retry.py
skala/pyscf/utils.py
skala/utils/__init__.py
skala/utils/scatter.py
microsoft_skala-1.1.1.dist-info/METADATA
microsoft_skala-1.1.1.dist-info/WHEEL
microsoft_skala-1.1.1.dist-info/top_level.txt
microsoft_skala-1.1.1.dist-info/RECORD
