Metadata-Version: 2.4
Name: microsoft-skala
Version: 1.1.1
Summary: Skala Exchange Correlation Functional
Project-URL: repository, https://github.com/microsoft/skala
Classifier: Programming Language :: Python :: 3
Classifier: Development Status :: 5 - Production/Stable
Requires-Python: >=3.10
License-File: LICENSE.txt
Requires-Dist: ase
Requires-Dist: azure-core
Requires-Dist: azure-identity
Requires-Dist: dftd3
Requires-Dist: e3nn
Requires-Dist: huggingface_hub
Requires-Dist: numpy
Requires-Dist: opt_einsum_fx
Requires-Dist: pyscf
Requires-Dist: qcelemental
Requires-Dist: torch
Provides-Extra: dev
Requires-Dist: pre-commit; extra == "dev"
Requires-Dist: pytest; extra == "dev"
Requires-Dist: pytest-cov; extra == "dev"
Provides-Extra: doc
Requires-Dist: myst-nb; extra == "doc"
Requires-Dist: sphinx; extra == "doc"
Requires-Dist: sphinx-book-theme; extra == "doc"
Dynamic: license-file
